{
"meta":{"test_sets":[],"test_metrics":[],"learn_metrics":[{"best_value":"Min","name":"Logloss"}],"launch_mode":"Train","parameters":"","iteration_count":30,"learn_sets":["learn"],"name":"experiment"},
"iterations":[
{"learn":[0.573389484],"iteration":0,"passed_time":0.06577458976,"remaining_time":1.907463103},
{"learn":[0.4830934155],"iteration":1,"passed_time":0.1227589538,"remaining_time":1.718625353},
{"learn":[0.4068450312],"iteration":2,"passed_time":0.1804487331,"remaining_time":1.624038598},
{"learn":[0.3530765657],"iteration":3,"passed_time":0.2382668905,"remaining_time":1.548734788},
{"learn":[0.3129978795],"iteration":4,"passed_time":0.2964335157,"remaining_time":1.482167578},
{"learn":[0.2769765854],"iteration":5,"passed_time":0.3537249002,"remaining_time":1.414899601},
{"learn":[0.2492498429],"iteration":6,"passed_time":0.413898283,"remaining_time":1.359951501},
{"learn":[0.2284213035],"iteration":7,"passed_time":0.4743194927,"remaining_time":1.304378605},
{"learn":[0.2074144425],"iteration":8,"passed_time":0.544279008,"remaining_time":1.269984352},
{"learn":[0.1914473349],"iteration":9,"passed_time":0.6011300826,"remaining_time":1.202260165},
{"learn":[0.1797345684],"iteration":10,"passed_time":0.6626429496,"remaining_time":1.144565095},
{"learn":[0.1666853351],"iteration":11,"passed_time":0.7220021521,"remaining_time":1.083003228},
{"learn":[0.155996538],"iteration":12,"passed_time":0.7788629283,"remaining_time":1.01851306},
{"learn":[0.1471905093],"iteration":13,"passed_time":0.8385458564,"remaining_time":0.9583381216},
{"learn":[0.1410077618],"iteration":14,"passed_time":0.9071749395,"remaining_time":0.9071749395},
{"learn":[0.1342738675],"iteration":15,"passed_time":0.9642239128,"remaining_time":0.8436959237},
{"learn":[0.1250255031],"iteration":16,"passed_time":1.02218487,"remaining_time":0.7816707827},
{"learn":[0.1176492168],"iteration":17,"passed_time":1.078761928,"remaining_time":0.7191746189},
{"learn":[0.1119618877],"iteration":18,"passed_time":1.136224478,"remaining_time":0.6578141713},
{"learn":[0.1065826339],"iteration":19,"passed_time":1.192470292,"remaining_time":0.5962351459},
{"learn":[0.1046540276],"iteration":20,"passed_time":1.251706043,"remaining_time":0.5364454469},
{"learn":[0.09875309852],"iteration":21,"passed_time":1.31242816,"remaining_time":0.4772466036},
{"learn":[0.09603995662],"iteration":22,"passed_time":1.369068094,"remaining_time":0.4166728981},
{"learn":[0.09428951048],"iteration":23,"passed_time":1.427705733,"remaining_time":0.3569264332},
{"learn":[0.08794627651],"iteration":24,"passed_time":1.485337583,"remaining_time":0.2970675166},
{"learn":[0.08628323001],"iteration":25,"passed_time":1.544672937,"remaining_time":0.2376419903},
{"learn":[0.08432603651],"iteration":26,"passed_time":1.602896756,"remaining_time":0.1780996396},
{"learn":[0.08198792704],"iteration":27,"passed_time":1.662764509,"remaining_time":0.1187688935},
{"learn":[0.07919210003],"iteration":28,"passed_time":1.718603824,"remaining_time":0.05926220082},
{"learn":[0.07646463763],"iteration":29,"passed_time":1.775908263,"remaining_time":0}
]}